metatomic/__init__.py
metatomic/torch/__init__.py
metatomic/torch/_c_lib.py
metatomic/torch/_extensions.py
metatomic/torch/ase_calculator.py
metatomic/torch/documentation.py
metatomic/torch/model.py
metatomic/torch/outputs.py
metatomic/torch/serialization.py
metatomic/torch/systems_to_torch.py
metatomic/torch/utils.py
metatomic/torch/version.py
metatomic/torch/torch-2.1/bin/metatomic_torch.dll
metatomic/torch/torch-2.1/include/metatomic/torch.hpp
metatomic/torch/torch-2.1/include/metatomic/torch/exports.h
metatomic/torch/torch-2.1/include/metatomic/torch/misc.hpp
metatomic/torch/torch-2.1/include/metatomic/torch/model.hpp
metatomic/torch/torch-2.1/include/metatomic/torch/system.hpp
metatomic/torch/torch-2.1/include/metatomic/torch/version.h
metatomic/torch/torch-2.1/lib/metatomic_torch.lib
metatomic/torch/torch-2.1/lib/cmake/metatomic_torch/metatomic_torch-config-version.cmake
metatomic/torch/torch-2.1/lib/cmake/metatomic_torch/metatomic_torch-config.cmake
metatomic/torch/torch-2.1/lib/cmake/metatomic_torch/metatomic_torch-targets-release.cmake
metatomic/torch/torch-2.1/lib/cmake/metatomic_torch/metatomic_torch-targets.cmake
metatomic/torch/torch-2.2/bin/metatomic_torch.dll
metatomic/torch/torch-2.2/include/metatomic/torch.hpp
metatomic/torch/torch-2.2/include/metatomic/torch/exports.h
metatomic/torch/torch-2.2/include/metatomic/torch/misc.hpp
metatomic/torch/torch-2.2/include/metatomic/torch/model.hpp
metatomic/torch/torch-2.2/include/metatomic/torch/system.hpp
metatomic/torch/torch-2.2/include/metatomic/torch/version.h
metatomic/torch/torch-2.2/lib/metatomic_torch.lib
metatomic/torch/torch-2.2/lib/cmake/metatomic_torch/metatomic_torch-config-version.cmake
metatomic/torch/torch-2.2/lib/cmake/metatomic_torch/metatomic_torch-config.cmake
metatomic/torch/torch-2.2/lib/cmake/metatomic_torch/metatomic_torch-targets-release.cmake
metatomic/torch/torch-2.2/lib/cmake/metatomic_torch/metatomic_torch-targets.cmake
metatomic/torch/torch-2.3/bin/metatomic_torch.dll
metatomic_torch-0.1.6.dist-info/licenses/AUTHORS
metatomic_torch-0.1.6.dist-info/licenses/LICENSE
metatomic_torch-0.1.6.dist-info/METADATA
metatomic_torch-0.1.6.dist-info/WHEEL
metatomic_torch-0.1.6.dist-info/top_level.txt
metatomic_torch-0.1.6.dist-info/RECORD
