Metadata-Version: 2.4
Name: metatomic-torch
Version: 0.1.6
Summary: Interface between atomistic machine learning models and simulation tools
Author: Guillaume Fraux, Filippo Bigi
License-Expression: BSD-3-Clause
Project-URL: homepage, https://docs.metatensor.org/metatomic/
Project-URL: documentation, https://docs.metatensor.org/metatomic/
Project-URL: repository, https://github.com/metatensor/metatomic
Project-URL: changelog, https://docs.metatensor.org/metatomic/latest/torch/CHANGELOG.html
Keywords: machine learning,molecular modeling,torch
Classifier: Development Status :: 4 - Beta
Classifier: Intended Audience :: Science/Research
Classifier: Operating System :: POSIX
Classifier: Operating System :: MacOS :: MacOS X
Classifier: Operating System :: Microsoft :: Windows
Classifier: Programming Language :: Python
Classifier: Programming Language :: Python :: 3
Classifier: Topic :: Scientific/Engineering
Classifier: Topic :: Scientific/Engineering :: Bio-Informatics
Classifier: Topic :: Scientific/Engineering :: Chemistry
Classifier: Topic :: Scientific/Engineering :: Physics
Classifier: Topic :: Software Development :: Libraries
Classifier: Topic :: Software Development :: Libraries :: Python Modules
Requires-Python: >=3.10
License-File: LICENSE
License-File: AUTHORS
Requires-Dist: torch >=2.1,<2.10
Requires-Dist: vesin
Requires-Dist: metatensor-torch<0.9,>=0.8.0
Requires-Dist: metatensor-operations<0.5,>=0.4.0
Dynamic: author
Dynamic: license-file
Dynamic: requires-dist
